{
  "positive": {
    "0到1": 30
  },
  "negative": {
    "过剩": -10,
    "竞争白热化": -20
  },
  "cagr_rules": [
    {
      "_comment": "同比增长规则：所有命中都落库。公司本体经营增长优先加分；宏观/行业/第三方统计句子记 neutral；费用成本类按负向处理。",
      "enabled": true,
      "phrase": "同比增长",
      "mode": "linear",
      "k": 0.1,
      "cap": 12,
      "min_pct": 20,
      "window_chars": 120,

      "neutralize_if_contains": [
          "数据显示",
          "统计数据显示",
          "根据",
          "白皮书",
          "研究报告",
          "国家能源局",
          "统计局",
          "海关总署",
          "国家数据局",
          "国家药监局",
          "国家电影局",
          "国家移民管理局",
          "中国汽车工业协会",
          "中国汽车动力电池产业创新联盟",
          "中国半导体行业协会",
          "证券业协会",
          "中关村储能产业技术联盟",
          "乘联会",
          "IDC",
          "Gartner",
          "TrendForce",
          "EVTank",
          "SIA",
          "WSTS",
          "Omdia",
          "GGII",
          "SNEResearch",
          "Sigmaintell",
          "艾瑞咨询",
          "艾媒咨询",
          "奥维云网",
          "全行业",
          "行业总体",
          "行业格局",
          "行业趋势",
          "行业情况",
          "市场规模",
          "市场份额",
          "累计装机",
          "装机容量",
          "累计并网",
          "全国",
          "我国",
          "国内",
          "全球",
          "全省",
          "研发投入",
          "研发费用",
          "研发人员",
          "预算"
      ],

      "negate_if_contains": [
        "销售费用",
        "管理费用",
        "营业成本"
      ],
      "negate_penalty_ratio": 0.5,

      "full_negate_if_contains": [
        "财务费用",
        "减值损失"
      ]
    }
  ]
}